txkernel/__init__.py
txkernel/connection.py
txkernel/kernelapp.py
txkernel/kernelbase.py
txkernel/message.py
txkernel/sockets.py
txkernel-0.1.0.dist-info/LICENSE
txkernel-0.1.0.dist-info/METADATA
txkernel-0.1.0.dist-info/WHEEL
txkernel-0.1.0.dist-info/top_level.txt
txkernel-0.1.0.dist-info/RECORD
