Metadata-Version: 2.1
Name: txkernel
Version: 0.1.0
Summary: Twisted based Jupyter kernel framework
Home-page: https://github.com/guysv/txkernel
Author: Guy Sviry
Author-email: sviryguy@gmail.com
License: GPLv2
Keywords: twisted async interactive console jupyter kernel
Platform: UNKNOWN
Classifier: Development Status :: 3 - Alpha
Classifier: Intended Audience :: Developers
Classifier: Topic :: Software Development :: Interpreters
Classifier: License :: OSI Approved :: GNU General Public License v2 (GPLv2)
Classifier: Operating System :: OS Independent
Classifier: Programming Language :: Python :: 2
Classifier: Programming Language :: Python :: 2.7
Classifier: Programming Language :: Python :: 3
Classifier: Programming Language :: Python :: 3.4
Classifier: Programming Language :: Python :: 3.5
Classifier: Programming Language :: Python :: 3.6
Classifier: Programming Language :: Python :: 3.7
Requires-Dist: twisted
Requires-Dist: txzmq
Requires-Dist: jupyter-core
